handler/__init__.py
handler/auth.py
handler/event.py
handler/handler.py
aimpf_dispatcher-0.1.0.dist-info/LICENSE
aimpf_dispatcher-0.1.0.dist-info/METADATA
aimpf_dispatcher-0.1.0.dist-info/WHEEL
aimpf_dispatcher-0.1.0.dist-info/top_level.txt
aimpf_dispatcher-0.1.0.dist-info/RECORD
