Metadata-Version: 2.1
Name: aimpf-dispatcher
Version: 0.1.0
Summary: A dispatcher to handle information from MQTT database
Author-email: Chen Chen <chen.chen@contextualize.us.com>, Branden Kappes <branden.kappes@contextualize.us.com>, William Silloway <william.silloway@contextualize.us.com>, Lindsey Kuettner <lindsey.kuettner@contextualize.us.com>
Project-URL: Homepage, https://gitlab.com/contextualize/operations/georgia-tech/aim-dsc-analysis
Classifier: Programming Language :: Python
Classifier: Programming Language :: Python :: 3
Classifier: License :: OSI Approved :: MIT License
Classifier: Operating System :: OS Independent
Requires-Python: >=3.10
License-File: LICENSE
Requires-Dist: aws-cdk-lib ==2.88.0
Requires-Dist: boto3
Requires-Dist: constructs <11.0.0,>=10.0.0
Requires-Dist: mysql-connector-python
Requires-Dist: nodeenv
Requires-Dist: pycognito
Requires-Dist: pydantic
Requires-Dist: pymysql
Requires-Dist: requests
Requires-Dist: sqlalchemy
Provides-Extra: dev
Requires-Dist: pytest ; extra == 'dev'
